SlySerialize/__init__.py
SlySerialize/_type_vars.py
SlySerialize/abc.py
SlySerialize/converters.py
SlySerialize/top_level.py
SlySerialize-0.0.2.dist-info/LICENSE
SlySerialize-0.0.2.dist-info/METADATA
SlySerialize-0.0.2.dist-info/WHEEL
SlySerialize-0.0.2.dist-info/top_level.txt
SlySerialize-0.0.2.dist-info/RECORD
