Metadata-Version: 2.1
Name: SlySerialize
Version: 0.0.2
Summary: Convert JSON-like data structures into nice Python objects.
Author: Dunkyl 🔣🔣
License: MIT License
Project-URL: Homepage, https://github.com/dunkyl/SlySerialize
Project-URL: Repository, https://github.com/dunkyl/SlySerialize
Project-URL: Documentation, https://docs.dunkyl.net/SlySerialize
Project-URL: Bug Tracker, https://github.com/dunkyl/SlySerialize/issues
Requires-Python: >=3.10
License-File: LICENSE
Provides-Extra: dev
Requires-Dist: pytest ; extra == 'dev'
Requires-Dist: pytest-asyncio ; extra == 'dev'
Requires-Dist: sphinx ; extra == 'dev'
Requires-Dist: myst-parser ; extra == 'dev'
Requires-Dist: furo ; extra == 'dev'
Requires-Dist: sphinxcontrib-trio ; extra == 'dev'
Requires-Dist: sphinx-copybutton ; extra == 'dev'
Requires-Dist: sphinxext-opengraph ; extra == 'dev'
